{
    "identifiable": false,
    "doc": "\\inqmlmodule org.nemomobile.social 1\n\\brief A FacebookPhotoTag represents a tag posted on a FacebookPhoto\n\nFacebookPhotoTag is a specialized ContentItem that is used to represent\na tag posted on a FacebookPhoto.\n\n\\sa{ContentItem}\n\\sa{FacebookPhoto}\n",
    "name": "photo_tag",
    "properties": [
        {
            "alias": "user_identifier",
            "type": "QString",
            "name": "id",
            "doc": "Holds the identifier of the tagged entity"
        },
        {
            "alias": "user_name",
            "doc": "Holds the name of the tagged entity",
            "type": "QString",
            "name": "name",
            "custom": true
        },
        {
            "doc": "Holds text that is used to tag something",
            "is_ontology": false,
            "type": "QString",
            "name": "text",
            "custom": true
        },
        {
            "doc": "Holds the x position of the tagged entity or text in the photo.\nThis coordinate is a percentage from the left edge of the photo.",
            "type": "float",
            "name": "x"
        },
        {
            "doc": "Holds the y position of the tagged entity or text in the photo.\nThis coordinate is a percentage from the top edge of the photo.",
            "type": "float",
            "name": "y"
        },
        {
            "doc": "Holds the creation time of the tag in an ISO8601-formatted string.",
            "type": "QString",
            "name": "created_time"
        }
    ]
}